py_docker_k8s_tasks/__init__.py
py_docker_k8s_tasks/django_tasks.py
py_docker_k8s_tasks/docker_tasks.py
py_docker_k8s_tasks/k8s_tasks.py
py_docker_k8s_tasks/util_tasks.py
inv_py_docker_k8s_tasks-0.1.14.dist-info/LICENSE.txt
inv_py_docker_k8s_tasks-0.1.14.dist-info/METADATA
inv_py_docker_k8s_tasks-0.1.14.dist-info/WHEEL
inv_py_docker_k8s_tasks-0.1.14.dist-info/top_level.txt
inv_py_docker_k8s_tasks-0.1.14.dist-info/RECORD
